{
  "wasp" :
    {
      "camera_TOP" :
        {
          "d_roll" :
            0.016177,
          "d_tilt" :
            -0.219083
        },
      "camera_BOT" :
        {
          "d_roll" :
            -0.000824,
          "d_tilt" :
            -0.161635
        }
    },
  "inara" :
    {
      "camera_TOP" :
        {
          "d_roll" :
            0,
          "d_tilt" :
            0
        },
      "camera_BOT" :
        {
          "d_roll" :
            0,
          "d_tilt" :
            0
        }
    },
  "blt" :
    {
      "camera_TOP" :
        {
          "d_roll" :
            0.026457,
          "d_tilt" :
            -0.234035
        },
      "camera_BOT" :
        {
          "d_roll" :
            0.020174,
          "d_tilt" :
            -0.081427
        }
    },
  "vera" :
    {
      "camera_TOP" :
        {
          "d_roll" :
            0,
          "d_tilt" :
            0
        },
      "camera_BOT" :
        {
          "d_roll" :
            0,
          "d_tilt" :
            0
        }
    },
  "buzz" :
    {
      "camera_TOP" :
        {
          "d_roll" :
            0.004054,
          "d_tilt" :
            -0.175443
        },
      "camera_BOT" :
        {
          "d_roll" :
            0.006837,
          "d_tilt" :
            -0.110732
        }
    },
  "wash" :
    {
      "camera_TOP" :
        {
          "d_roll" :
            -0.013589,
          "d_tilt" :
            -0.052398
        },
      "camera_BOT" :
        {
          "d_roll" :
            -0.013021,
          "d_tilt" :
            -0.042207
        }
    },
  "none" :
    {
      "camera_TOP" :
        {
          "d_roll" :
            0,
          "d_tilt" :
            0
        },
      "camera_BOT" :
        {
          "d_roll" :
            0,
          "d_tilt" :
            0
        }
    },
  "batman" :
    {
      "camera_TOP" :
        {
          "d_roll" :
            -0.032507,
          "d_tilt" :
            -0.15329
        },
      "camera_BOT" :
        {
          "d_roll" :
            -0.008063,
          "d_tilt" :
            -0.143226
        }
    },
  "mal" :
    {
      "camera_TOP" :
        {
          "d_roll" :
            -0.113934,
          "d_tilt" :
            -0.055559
        },
      "camera_BOT" :
        {
          "d_roll" :
            -0.043646,
          "d_tilt" :
            -0.024966
        }
    },
  "simon" :
    {
      "camera_TOP" :
        {
          "d_roll" :
            -0.009851,
          "d_tilt" :
            -0.158193
        },
      "camera_BOT" :
        {
          "d_roll" :
            0.002643,
          "d_tilt" :
            -0.185518
        }
    },
  "elektra" :
    {
      "camera_TOP" :
        {
          "d_roll" :
            0.006732,
          "d_tilt" :
            -0.183121
        },
      "camera_BOT" :
        {
          "d_roll" :
            -0.026898,
          "d_tilt" :
            -0.114153
        }
    },
  "shehulk" :
    {
      "camera_TOP" :
        {
          "d_roll" :
            0.012212,
          "d_tilt" :
            -0.204698
        },
      "camera_BOT" :
        {
          "d_roll" :
            0.042942,
          "d_tilt" :
            -0.132761
        }
    },
  "kaylee" :
    {
      "camera_TOP" :
        {
          "d_roll" :
            0.003291,
          "d_tilt" :
            0.340564
        },
      "camera_BOT" :
        {
          "d_roll" :
            -0.016782,
          "d_tilt" :
            0.001572
        }
    },
  "jayne" :
    {
      "camera_TOP" :
        {
          "d_roll" :
            0,
          "d_tilt" :
            0
        },
      "camera_BOT" :
        {
          "d_roll" :
            0,
          "d_tilt" :
            0
        }
    },
  "zoe" :
    {
      "camera_TOP" :
        {
          "d_roll" :
            -0.043916,
          "d_tilt" :
            -0.148018
        },
      "camera_BOT" :
        {
          "d_roll" :
            -0.031652,
          "d_tilt" :
            -0.147916
        }
    },
  "river" :
    {
      "camera_TOP" :
        {
          "d_roll" :
            0,
          "d_tilt" :
            0
        },
      "camera_BOT" :
        {
          "d_roll" :
            0,
          "d_tilt" :
            0
        }
    }
}